[
    {
        "summary": {
            "status": "success",
            "zero_load_latency": 165.125,
            "saturation_throughput": 0.005,
            "total_router_area": 90.3166497519264,
            "total_router_power": 25.263358181527998,
            "total_link_power": 0.3628787199999999,
            "energy_per_packet": 160.16398063455
        },
        "orion_details": {
            "Pleakage": 1009.103752552,
            "Pinternal": 15924.382173440003,
            "Pswitching": 8329.872255535998,
            "Ainbuffer": 89365521.28,
            "Aoutbuffer": 416996.822944,
            "Acrossbar": 176667.094016,
            "Aswvc": 289095.00820800004,
            "Aclkctrl": 68369.54675839999,
            "Atotal": 90316649.7519264,
            "Ptotal": 25263.358181527998
        },
        "orion_config": {
            "n_vcs": 4,
            "vc_buf_size": 16,
            "frequency": 1000000000.0,
            "data_width": 64
        },
        "experiment_config": {
            "nodes_per_router": 1,
            "node_link_latency": 5,
            "width": 8.6,
            "height": 8.6,
            "num_vcs": 4,
            "vc_buf_size": 16,
            "packet_size": 4,
            "message_size": 16,
            "in_order_ratio": 0.5,
            "frequency": 1000000000.0,
            "data_width": 64,
            "link_fault_rate": 0.0,
            "router_fault_rate": 0.0,
            "n_entropy_bits": 8,
            "traffic": "uniform",
            "topology": "kite_small",
            "n_routers": 64,
            "routing_function": "multi_routing",
            "mod_routing_function": "left_right",
            "mod_selection_function": "adaptive",
            "name": "vary_topo_aici_uniform_kite_small_multi_routing_left_right_adaptive",
            "plot_type": "heatmap"
        },
        "booksim_details": {
            "0.001": {
                "return_code": 0,
                "status": "Success",
                "runtime": 18.477404698729515,
                "cdg_check": "unknown",
                "packet_latency": {
                    "avg": 165.125,
                    "min": 18.0,
                    "max": 349.0
                },
                "network_latency": {
                    "avg": 127.322,
                    "min": 18.0,
                    "max": 263.0
                },
                "flit_latency": {
                    "avg": 124.302,
                    "min": 15.0,
                    "max": 260.0
                },
                "fragmentation": {
                    "avg": 0.0239286,
                    "min": 0.0,
                    "max": 6.0
                },
                "injected_packet_rate": {
                    "avg": 0.000273438,
                    "min": 0.0,
                    "max": 0.0008
                },
                "accepted_packet_rate": {
                    "avg": 0.000273438,
                    "min": 0.0,
                    "max": 0.0008
                },
                "injected_flit_rate": {
                    "avg": 0.00109375,
                    "min": 0.0,
                    "max": 0.0032
                },
                "accepted_flit_rate": {
                    "avg": 0.00109375,
                    "min": 0.0,
                    "max": 0.0032
                },
                "injected_packet_size": {
                    "avg": 4.0
                },
                "accepted_packet_size": {
                    "avg": 4.0
                },
                "hops": {
                    "avg": 6.82857
                },
                "total_ooo_packets": 0,
                "peak_rob_size": 0,
                "peak_robs_per_node": 0,
                "selection_function_storage_overhead": 0,
                "total_run_time": 18.3422,
                "number_of_deadlocked_runs": 0
            },
            "0.002": {
                "return_code": 0,
                "status": "Success",
                "runtime": 19.70807883143425,
                "cdg_check": "unknown",
                "packet_latency": {
                    "avg": 164.018,
                    "min": 18.0,
                    "max": 327.0
                },
                "network_latency": {
                    "avg": 126.899,
                    "min": 18.0,
                    "max": 247.0
                },
                "flit_latency": {
                    "avg": 123.879,
                    "min": 15.0,
                    "max": 244.0
                },
                "fragmentation": {
                    "avg": 0.0275383,
                    "min": 0.0,
                    "max": 5.0
                },
                "injected_packet_rate": {
                    "avg": 0.000543099,
                    "min": 0.0,
                    "max": 0.0012
                },
                "accepted_packet_rate": {
                    "avg": 0.000539193,
                    "min": 0.0,
                    "max": 0.00133333
                },
                "injected_flit_rate": {
                    "avg": 0.0021724,
                    "min": 0.0,
                    "max": 0.0048
                },
                "accepted_flit_rate": {
                    "avg": 0.00215677,
                    "min": 0.0,
                    "max": 0.00533333
                },
                "injected_packet_size": {
                    "avg": 4.0
                },
                "accepted_packet_size": {
                    "avg": 4.0
                },
                "hops": {
                    "avg": 6.6705
                },
                "total_ooo_packets": 0,
                "peak_rob_size": 0,
                "peak_robs_per_node": 0,
                "selection_function_storage_overhead": 0,
                "total_run_time": 19.5731,
                "number_of_deadlocked_runs": 0
            },
            "0.003": {
                "return_code": 0,
                "status": "Success",
                "runtime": 28.021497890353203,
                "cdg_check": "unknown",
                "packet_latency": {
                    "avg": 168.472,
                    "min": 18.0,
                    "max": 373.0
                },
                "network_latency": {
                    "avg": 130.601,
                    "min": 18.0,
                    "max": 244.0
                },
                "flit_latency": {
                    "avg": 127.612,
                    "min": 15.0,
                    "max": 241.0
                },
                "fragmentation": {
                    "avg": 0.0389895,
                    "min": 0.0,
                    "max": 5.0
                },
                "injected_packet_rate": {
                    "avg": 0.000764286,
                    "min": 0.000114286,
                    "max": 0.0016
                },
                "accepted_packet_rate": {
                    "avg": 0.000763393,
                    "min": 0.000342857,
                    "max": 0.00137143
                },
                "injected_flit_rate": {
                    "avg": 0.00305714,
                    "min": 0.000457143,
                    "max": 0.0064
                },
                "accepted_flit_rate": {
                    "avg": 0.00305357,
                    "min": 0.00137143,
                    "max": 0.00548571
                },
                "injected_packet_size": {
                    "avg": 4.0
                },
                "accepted_packet_size": {
                    "avg": 4.0
                },
                "hops": {
                    "avg": 7.00234
                },
                "total_ooo_packets": 0,
                "peak_rob_size": 0,
                "peak_robs_per_node": 0,
                "selection_function_storage_overhead": 0,
                "total_run_time": 27.8824,
                "number_of_deadlocked_runs": 0
            },
            "0.004": {
                "return_code": 0,
                "status": "Success",
                "runtime": 21.349426686763763,
                "cdg_check": "unknown",
                "packet_latency": {
                    "avg": 160.503,
                    "min": 18.0,
                    "max": 332.0
                },
                "network_latency": {
                    "avg": 123.038,
                    "min": 18.0,
                    "max": 254.0
                },
                "flit_latency": {
                    "avg": 120.026,
                    "min": 15.0,
                    "max": 251.0
                },
                "fragmentation": {
                    "avg": 0.0415441,
                    "min": 0.0,
                    "max": 8.0
                },
                "injected_packet_rate": {
                    "avg": 0.0010625,
                    "min": 0.0002,
                    "max": 0.0024
                },
                "accepted_packet_rate": {
                    "avg": 0.00106289,
                    "min": 0.0002,
                    "max": 0.0026
                },
                "injected_flit_rate": {
                    "avg": 0.00425,
                    "min": 0.0008,
                    "max": 0.0096
                },
                "accepted_flit_rate": {
                    "avg": 0.00425156,
                    "min": 0.0008,
                    "max": 0.0104
                },
                "injected_packet_size": {
                    "avg": 4.0
                },
                "accepted_packet_size": {
                    "avg": 4.0
                },
                "hops": {
                    "avg": 6.44301
                },
                "total_ooo_packets": 0,
                "peak_rob_size": 0,
                "peak_robs_per_node": 0,
                "selection_function_storage_overhead": 0,
                "total_run_time": 21.2109,
                "number_of_deadlocked_runs": 0
            },
            "0.005": {
                "return_code": 0,
                "status": "Success",
                "runtime": 20.50161412358284,
                "cdg_check": "unknown",
                "packet_latency": {
                    "avg": 163.65,
                    "min": 18.0,
                    "max": 356.0
                },
                "network_latency": {
                    "avg": 126.216,
                    "min": 18.0,
                    "max": 276.0
                },
                "flit_latency": {
                    "avg": 123.134,
                    "min": 15.0,
                    "max": 273.0
                },
                "fragmentation": {
                    "avg": 0.0478175,
                    "min": 0.0,
                    "max": 6.0
                },
                "injected_packet_rate": {
                    "avg": 0.0013125,
                    "min": 0.000266667,
                    "max": 0.00266667
                },
                "accepted_packet_rate": {
                    "avg": 0.00131172,
                    "min": 0.000266667,
                    "max": 0.00266667
                },
                "injected_flit_rate": {
                    "avg": 0.00525,
                    "min": 0.00106667,
                    "max": 0.0106667
                },
                "accepted_flit_rate": {
                    "avg": 0.00524766,
                    "min": 0.00106667,
                    "max": 0.0106667
                },
                "injected_packet_size": {
                    "avg": 4.0
                },
                "accepted_packet_size": {
                    "avg": 4.0006
                },
                "hops": {
                    "avg": 6.63512
                },
                "total_ooo_packets": 0,
                "peak_rob_size": 0,
                "peak_robs_per_node": 0,
                "selection_function_storage_overhead": 0,
                "total_run_time": 20.3502,
                "number_of_deadlocked_runs": 1
            },
            "0.006": {
                "return_code": 2,
                "status": "Unstable simulation",
                "runtime": 28.29922378063202,
                "cdg_check": "unknown",
                "packet_latency": {
                    "avg": 160.218,
                    "min": 18.0,
                    "max": 317.0
                },
                "network_latency": {
                    "avg": 122.626,
                    "min": 18.0,
                    "max": 245.0
                },
                "flit_latency": {
                    "avg": 119.67,
                    "min": 15.0,
                    "max": 242.0
                },
                "fragmentation": {
                    "avg": 0.0421561,
                    "min": 0.0,
                    "max": 5.0
                },
                "injected_packet_rate": {
                    "avg": 0.00149414,
                    "min": 0.0004,
                    "max": 0.0028
                },
                "accepted_packet_rate": {
                    "avg": 0.00121641,
                    "min": 0.000375,
                    "max": 0.00225
                },
                "injected_flit_rate": {
                    "avg": 0.00597656,
                    "min": 0.0016,
                    "max": 0.0112
                },
                "accepted_flit_rate": {
                    "avg": NaN,
                    "min": 0.0015,
                    "max": 0.009
                },
                "total_run_time": 28.173,
                "number_of_deadlocked_runs": 0
            },
            "0.01": {
                "return_code": 2,
                "status": "Unstable simulation",
                "runtime": 23.20199792087078,
                "cdg_check": "unknown",
                "packet_latency": {
                    "avg": 154.754,
                    "min": 18.0,
                    "max": 310.0
                },
                "network_latency": {
                    "avg": 117.402,
                    "min": 18.0,
                    "max": 261.0
                },
                "flit_latency": {
                    "avg": 114.553,
                    "min": 15.0,
                    "max": 258.0
                },
                "fragmentation": {
                    "avg": 0.052973,
                    "min": 0.0,
                    "max": 5.0
                },
                "injected_packet_rate": {
                    "avg": 0.00216406,
                    "min": 0.0006,
                    "max": 0.00445
                },
                "accepted_packet_rate": {
                    "avg": 0.00145156,
                    "min": 0.0,
                    "max": 0.003725
                },
                "injected_flit_rate": {
                    "avg": 0.00865664,
                    "min": 0.0024,
                    "max": 0.0178
                },
                "accepted_flit_rate": {
                    "avg": NaN,
                    "min": 0.0,
                    "max": 0.0149
                },
                "total_run_time": 23.0532,
                "number_of_deadlocked_runs": 0
            },
            "0.1": {
                "return_code": 2,
                "status": "Unstable simulation",
                "runtime": 16.768019556999207,
                "cdg_check": "unknown",
                "packet_latency": {
                    "avg": 170.115,
                    "min": 18.0,
                    "max": 454.0
                },
                "network_latency": {
                    "avg": 124.576,
                    "min": 18.0,
                    "max": 367.0
                },
                "flit_latency": {
                    "avg": 121.244,
                    "min": 15.0,
                    "max": 364.0
                },
                "fragmentation": {
                    "avg": 0.36432,
                    "min": 0.0,
                    "max": 13.0
                },
                "injected_packet_rate": {
                    "avg": 0.00382031,
                    "min": 0.0012,
                    "max": 0.0082
                },
                "accepted_packet_rate": {
                    "avg": 0.001975,
                    "min": 0.0,
                    "max": 0.0048
                },
                "injected_flit_rate": {
                    "avg": 0.0152812,
                    "min": 0.0048,
                    "max": 0.0328
                },
                "accepted_flit_rate": {
                    "avg": NaN,
                    "min": 0.0,
                    "max": 0.0192
                },
                "total_run_time": 16.6255,
                "number_of_deadlocked_runs": 0
            }
        },
        "booksim_config": {
            "deadlock_attempts": 10,
            "seed": "time",
            "ignore_cycles": 1,
            "trace_time_out": 7200,
            "precision": 0.001,
            "saturation_factor": 2,
            "router_latency": 3,
            "warmup_periods": 1,
            "sim_count": 1,
            "hold_switch_for_packet": 0,
            "vc_allocator": "separable_input_first",
            "sw_allocator": "separable_input_first",
            "alloc_iters": 1,
            "wait_for_tail_credit": 0,
            "priority": "none",
            "injection_rate_uses_flits": 1,
            "deadlock_warn_timeout": 200000,
            "time_limit": 43200,
            "latency_thres": 5000.0,
            "routing_function": "multi_routing",
            "modular_routing_function": "left_right",
            "modular_selection_function": "adaptive",
            "num_vcs": 4,
            "vc_buf_size": 16,
            "packet_size": 4,
            "message_size": 16,
            "in_order_ratio": 0.5,
            "n_entropy_bits": 8,
            "threshold_mode": "bounded",
            "mode": "traffic",
            "traffic": "uniform",
            "trace_file": null,
            "sample_period": 20000,
            "repetition": 2
        }
    },
    {
        "summary": {
            "status": "success",
            "zero_load_latency": 164.344,
            "saturation_throughput": 0.002,
            "total_router_area": 90.3166497519264,
            "total_router_power": 25.263358181527998,
            "total_link_power": 0.3628787199999999,
            "energy_per_packet": 160.16398063455
        },
        "orion_details": {
            "Pleakage": 1009.103752552,
            "Pinternal": 15924.382173440003,
            "Pswitching": 8329.872255535998,
            "Ainbuffer": 89365521.28,
            "Aoutbuffer": 416996.822944,
            "Acrossbar": 176667.094016,
            "Aswvc": 289095.00820800004,
            "Aclkctrl": 68369.54675839999,
            "Atotal": 90316649.7519264,
            "Ptotal": 25263.358181527998
        },
        "orion_config": {
            "n_vcs": 4,
            "vc_buf_size": 16,
            "frequency": 1000000000.0,
            "data_width": 64
        },
        "experiment_config": {
            "nodes_per_router": 1,
            "node_link_latency": 5,
            "width": 8.6,
            "height": 8.6,
            "num_vcs": 4,
            "vc_buf_size": 16,
            "packet_size": 4,
            "message_size": 16,
            "in_order_ratio": 0.5,
            "frequency": 1000000000.0,
            "data_width": 64,
            "link_fault_rate": 0.0,
            "router_fault_rate": 0.0,
            "n_entropy_bits": 8,
            "traffic": "uniform",
            "topology": "kite_small",
            "n_routers": 64,
            "routing_function": "multi_routing",
            "mod_routing_function": "left_right",
            "mod_selection_function": "adaptive",
            "name": "vary_topo_aici_uniform_kite_small_multi_routing_left_right_adaptive",
            "plot_type": "heatmap"
        },
        "booksim_details": {
            "0.001": {
                "return_code": 0,
                "status": "Success",
                "runtime": 15.171049237251282,
                "cdg_check": "unknown",
                "packet_latency": {
                    "avg": 164.344,
                    "min": 31.0,
                    "max": 319.0
                },
                "network_latency": {
                    "avg": 127.334,
                    "min": 31.0,
                    "max": 241.0
                },
                "flit_latency": {
                    "avg": 124.314,
                    "min": 28.0,
                    "max": 238.0
                },
                "fragmentation": {
                    "avg": 0.0281762,
                    "min": 0.0,
                    "max": 4.0
                },
                "injected_packet_rate": {
                    "avg": 0.000217857,
                    "min": 0.0,
                    "max": 0.000571429
                },
                "accepted_packet_rate": {
                    "avg": 0.000217857,
                    "min": 0.0,
                    "max": 0.000685714
                },
                "injected_flit_rate": {
                    "avg": 0.000871429,
                    "min": 0.0,
                    "max": 0.00228571
                },
                "accepted_flit_rate": {
                    "avg": 0.000871429,
                    "min": 0.0,
                    "max": 0.00274286
                },
                "injected_packet_size": {
                    "avg": 4.0
                },
                "accepted_packet_size": {
                    "avg": 4.0
                },
                "hops": {
                    "avg": 6.73668
                },
                "total_ooo_packets": 0,
                "peak_rob_size": 0,
                "peak_robs_per_node": 0,
                "selection_function_storage_overhead": 0,
                "total_run_time": 15.0378,
                "number_of_deadlocked_runs": 0
            },
            "0.002": {
                "return_code": 0,
                "status": "Success",
                "runtime": 21.882449969649315,
                "cdg_check": "unknown",
                "packet_latency": {
                    "avg": 172.342,
                    "min": 18.0,
                    "max": 319.0
                },
                "network_latency": {
                    "avg": 135.358,
                    "min": 18.0,
                    "max": 245.0
                },
                "flit_latency": {
                    "avg": 132.191,
                    "min": 15.0,
                    "max": 242.0
                },
                "fragmentation": {
                    "avg": 0.0226884,
                    "min": 0.0,
                    "max": 6.0
                },
                "injected_packet_rate": {
                    "avg": 0.000521429,
                    "min": 0.0,
                    "max": 0.00114286
                },
                "accepted_packet_rate": {
                    "avg": 0.000522768,
                    "min": 0.000114286,
                    "max": 0.00114286
                },
                "injected_flit_rate": {
                    "avg": 0.00208571,
                    "min": 0.0,
                    "max": 0.00457143
                },
                "accepted_flit_rate": {
                    "avg": 0.00209085,
                    "min": 0.000457143,
                    "max": 0.00457143
                },
                "injected_packet_size": {
                    "avg": 4.0
                },
                "accepted_packet_size": {
                    "avg": 3.99957
                },
                "hops": {
                    "avg": 7.23609
                },
                "total_ooo_packets": 0,
                "peak_rob_size": 0,
                "peak_robs_per_node": 0,
                "selection_function_storage_overhead": 0,
                "total_run_time": 21.7494,
                "number_of_deadlocked_runs": 0
            },
            "0.003": {
                "return_code": 2,
                "status": "Unstable simulation",
                "runtime": 9.373976722359657,
                "cdg_check": "unknown",
                "packet_latency": {
                    "avg": 159.435,
                    "min": 31.0,
                    "max": 313.0
                },
                "network_latency": {
                    "avg": 122.619,
                    "min": 31.0,
                    "max": 252.0
                },
                "flit_latency": {
                    "avg": 119.588,
                    "min": 28.0,
                    "max": 249.0
                },
                "fragmentation": {
                    "avg": 0.0300871,
                    "min": 0.0,
                    "max": 3.0
                },
                "injected_packet_rate": {
                    "avg": 0.000675391,
                    "min": 0.0,
                    "max": 0.0024
                },
                "accepted_packet_rate": {
                    "avg": 0.000493359,
                    "min": 0.0,
                    "max": 0.0016
                },
                "injected_flit_rate": {
                    "avg": 0.00270156,
                    "min": 0.0,
                    "max": 0.0096
                },
                "accepted_flit_rate": {
                    "avg": NaN,
                    "min": 0.0,
                    "max": 0.0064
                },
                "total_run_time": 9.24295,
                "number_of_deadlocked_runs": 0
            },
            "0.01": {
                "return_code": 2,
                "status": "Unstable simulation",
                "runtime": 32.86601120233536,
                "cdg_check": "unknown",
                "packet_latency": {
                    "avg": 153.971,
                    "min": 18.0,
                    "max": 342.0
                },
                "network_latency": {
                    "avg": 116.605,
                    "min": 18.0,
                    "max": 292.0
                },
                "flit_latency": {
                    "avg": 113.525,
                    "min": 15.0,
                    "max": 289.0
                },
                "fragmentation": {
                    "avg": 0.0653141,
                    "min": 0.0,
                    "max": 11.0
                },
                "injected_packet_rate": {
                    "avg": 0.00197943,
                    "min": 0.000416667,
                    "max": 0.00396667
                },
                "accepted_packet_rate": {
                    "avg": 0.00147578,
                    "min": 0.000266667,
                    "max": 0.00295
                },
                "injected_flit_rate": {
                    "avg": 0.00791875,
                    "min": 0.00166667,
                    "max": 0.0158667
                },
                "accepted_flit_rate": {
                    "avg": NaN,
                    "min": 0.00106667,
                    "max": 0.0118
                },
                "total_run_time": 32.7255,
                "number_of_deadlocked_runs": 0
            },
            "0.1": {
                "return_code": 2,
                "status": "Unstable simulation",
                "runtime": 17.828505650162697,
                "cdg_check": "unknown",
                "packet_latency": {
                    "avg": 189.039,
                    "min": 18.0,
                    "max": 561.0
                },
                "network_latency": {
                    "avg": 141.884,
                    "min": 18.0,
                    "max": 481.0
                },
                "flit_latency": {
                    "avg": 138.494,
                    "min": 15.0,
                    "max": 478.0
                },
                "fragmentation": {
                    "avg": 0.473239,
                    "min": 0.0,
                    "max": 29.0
                },
                "injected_packet_rate": {
                    "avg": 0.00417422,
                    "min": 0.00095,
                    "max": 0.00675
                },
                "accepted_packet_rate": {
                    "avg": 0.00221875,
                    "min": 0.0,
                    "max": 0.0056
                },
                "injected_flit_rate": {
                    "avg": 0.0166969,
                    "min": 0.0038,
                    "max": 0.027
                },
                "accepted_flit_rate": {
                    "avg": NaN,
                    "min": 0.0,
                    "max": 0.0224
                },
                "total_run_time": 17.7043,
                "number_of_deadlocked_runs": 0
            }
        },
        "booksim_config": {
            "deadlock_attempts": 10,
            "seed": "time",
            "ignore_cycles": 1,
            "trace_time_out": 7200,
            "precision": 0.001,
            "saturation_factor": 2,
            "router_latency": 3,
            "warmup_periods": 1,
            "sim_count": 1,
            "hold_switch_for_packet": 0,
            "vc_allocator": "separable_input_first",
            "sw_allocator": "separable_input_first",
            "alloc_iters": 1,
            "wait_for_tail_credit": 0,
            "priority": "none",
            "injection_rate_uses_flits": 1,
            "deadlock_warn_timeout": 200000,
            "time_limit": 43200,
            "latency_thres": 5000.0,
            "routing_function": "multi_routing",
            "modular_routing_function": "left_right",
            "modular_selection_function": "adaptive",
            "num_vcs": 4,
            "vc_buf_size": 16,
            "packet_size": 4,
            "message_size": 16,
            "in_order_ratio": 0.5,
            "n_entropy_bits": 8,
            "threshold_mode": "bounded",
            "mode": "traffic",
            "traffic": "uniform",
            "trace_file": null,
            "sample_period": 20000,
            "repetition": 2
        }
    },
    {
        "summary": {
            "status": "success",
            "zero_load_latency": 160.123,
            "saturation_throughput": 0.01,
            "total_router_area": 90.3166497519264,
            "total_router_power": 25.263358181527998,
            "total_link_power": 0.3628787199999999,
            "energy_per_packet": 160.16398063455
        },
        "orion_details": {
            "Pleakage": 1009.103752552,
            "Pinternal": 15924.382173440003,
            "Pswitching": 8329.872255535998,
            "Ainbuffer": 89365521.28,
            "Aoutbuffer": 416996.822944,
            "Acrossbar": 176667.094016,
            "Aswvc": 289095.00820800004,
            "Aclkctrl": 68369.54675839999,
            "Atotal": 90316649.7519264,
            "Ptotal": 25263.358181527998
        },
        "orion_config": {
            "n_vcs": 4,
            "vc_buf_size": 16,
            "frequency": 1000000000.0,
            "data_width": 64
        },
        "experiment_config": {
            "nodes_per_router": 1,
            "node_link_latency": 5,
            "width": 8.6,
            "height": 8.6,
            "num_vcs": 4,
            "vc_buf_size": 16,
            "packet_size": 4,
            "message_size": 16,
            "in_order_ratio": 0.5,
            "frequency": 1000000000.0,
            "data_width": 64,
            "link_fault_rate": 0.0,
            "router_fault_rate": 0.0,
            "n_entropy_bits": 8,
            "traffic": "uniform",
            "topology": "kite_small",
            "n_routers": 64,
            "routing_function": "multi_routing",
            "mod_routing_function": "left_right",
            "mod_selection_function": "adaptive",
            "name": "vary_topo_aici_uniform_kite_small_multi_routing_left_right_adaptive",
            "plot_type": "heatmap"
        },
        "booksim_details": {
            "0.001": {
                "return_code": 0,
                "status": "Success",
                "runtime": 16.230350017547607,
                "cdg_check": "unknown",
                "packet_latency": {
                    "avg": 160.123,
                    "min": 31.0,
                    "max": 319.0
                },
                "network_latency": {
                    "avg": 123.066,
                    "min": 31.0,
                    "max": 245.0
                },
                "flit_latency": {
                    "avg": 120.055,
                    "min": 28.0,
                    "max": 242.0
                },
                "fragmentation": {
                    "avg": 0.0147293,
                    "min": 0.0,
                    "max": 6.0
                },
                "injected_packet_rate": {
                    "avg": 0.000245312,
                    "min": 0.0,
                    "max": 0.0006
                },
                "accepted_packet_rate": {
                    "avg": 0.000243945,
                    "min": 0.0,
                    "max": 0.0006
                },
                "injected_flit_rate": {
                    "avg": 0.00098125,
                    "min": 0.0,
                    "max": 0.0024
                },
                "accepted_flit_rate": {
                    "avg": 0.000975781,
                    "min": 0.0,
                    "max": 0.0024
                },
                "injected_packet_size": {
                    "avg": 4.0
                },
                "accepted_packet_size": {
                    "avg": 4.0
                },
                "hops": {
                    "avg": 6.73169
                },
                "total_ooo_packets": 0,
                "peak_rob_size": 0,
                "peak_robs_per_node": 0,
                "selection_function_storage_overhead": 0,
                "total_run_time": 16.1017,
                "number_of_deadlocked_runs": 0
            },
            "0.002": {
                "return_code": 0,
                "status": "Success",
                "runtime": 19.327286660671234,
                "cdg_check": "unknown",
                "packet_latency": {
                    "avg": 158.273,
                    "min": 18.0,
                    "max": 348.0
                },
                "network_latency": {
                    "avg": 121.094,
                    "min": 18.0,
                    "max": 241.0
                },
                "flit_latency": {
                    "avg": 118.064,
                    "min": 15.0,
                    "max": 238.0
                },
                "fragmentation": {
                    "avg": 0.0310168,
                    "min": 0.0,
                    "max": 4.0
                },
                "injected_packet_rate": {
                    "avg": 0.000479129,
                    "min": 0.0,
                    "max": 0.00114286
                },
                "accepted_packet_rate": {
                    "avg": 0.000478571,
                    "min": 0.0,
                    "max": 0.00102857
                },
                "injected_flit_rate": {
                    "avg": 0.00191663,
                    "min": 0.0,
                    "max": 0.00457143
                },
                "accepted_flit_rate": {
                    "avg": 0.00191429,
                    "min": 0.0,
                    "max": 0.00411429
                },
                "injected_packet_size": {
                    "avg": 4.00023
                },
                "accepted_packet_size": {
                    "avg": 4.0
                },
                "hops": {
                    "avg": 6.5021
                },
                "total_ooo_packets": 0,
                "peak_rob_size": 0,
                "peak_robs_per_node": 0,
                "selection_function_storage_overhead": 0,
                "total_run_time": 19.1955,
                "number_of_deadlocked_runs": 0
            },
            "0.003": {
                "return_code": 0,
                "status": "Success",
                "runtime": 18.785005941987038,
                "cdg_check": "unknown",
                "packet_latency": {
                    "avg": 160.273,
                    "min": 18.0,
                    "max": 311.0
                },
                "network_latency": {
                    "avg": 123.231,
                    "min": 18.0,
                    "max": 232.0
                },
                "flit_latency": {
                    "avg": 120.206,
                    "min": 15.0,
                    "max": 229.0
                },
                "fragmentation": {
                    "avg": 0.0295493,
                    "min": 0.0,
                    "max": 4.0
                },
                "injected_packet_rate": {
                    "avg": 0.000735,
                    "min": 0.00016,
                    "max": 0.00176
                },
                "accepted_packet_rate": {
                    "avg": 0.000735,
                    "min": 0.0,
                    "max": 0.0016
                },
                "injected_flit_rate": {
                    "avg": 0.00294,
                    "min": 0.00064,
                    "max": 0.00704
                },
                "accepted_flit_rate": {
                    "avg": 0.00294,
                    "min": 0.0,
                    "max": 0.0064
                },
                "injected_packet_size": {
                    "avg": 4.0
                },
                "accepted_packet_size": {
                    "avg": 4.0
                },
                "hops": {
                    "avg": 6.55889
                },
                "total_ooo_packets": 0,
                "peak_rob_size": 0,
                "peak_robs_per_node": 0,
                "selection_function_storage_overhead": 0,
                "total_run_time": 18.6527,
                "number_of_deadlocked_runs": 0
            },
            "0.004": {
                "return_code": 0,
                "status": "Success",
                "runtime": 30.307472079992294,
                "cdg_check": "unknown",
                "packet_latency": {
                    "avg": 161.663,
                    "min": 18.0,
                    "max": 354.0
                },
                "network_latency": {
                    "avg": 124.237,
                    "min": 18.0,
                    "max": 260.0
                },
                "flit_latency": {
                    "avg": 121.244,
                    "min": 15.0,
                    "max": 257.0
                },
                "fragmentation": {
                    "avg": 0.0519713,
                    "min": 0.0,
                    "max": 10.0
                },
                "injected_packet_rate": {
                    "avg": 0.000995313,
                    "min": 0.000342857,
                    "max": 0.00194286
                },
                "accepted_packet_rate": {
                    "avg": 0.000993862,
                    "min": 0.000342857,
                    "max": 0.00164286
                },
                "injected_flit_rate": {
                    "avg": 0.00398103,
                    "min": 0.00137143,
                    "max": 0.00777143
                },
                "accepted_flit_rate": {
                    "avg": 0.00397556,
                    "min": 0.00137143,
                    "max": 0.00657143
                },
                "injected_packet_size": {
                    "avg": 3.99978
                },
                "accepted_packet_size": {
                    "avg": 4.00011
                },
                "hops": {
                    "avg": 6.51949
                },
                "total_ooo_packets": 0,
                "peak_rob_size": 0,
                "peak_robs_per_node": 0,
                "selection_function_storage_overhead": 0,
                "total_run_time": 30.172,
                "number_of_deadlocked_runs": 0
            },
            "0.005": {
                "return_code": 0,
                "status": "Success",
                "runtime": 38.311764255166054,
                "cdg_check": "unknown",
                "packet_latency": {
                    "avg": 173.929,
                    "min": 18.0,
                    "max": 356.0
                },
                "network_latency": {
                    "avg": 136.869,
                    "min": 18.0,
                    "max": 283.0
                },
                "flit_latency": {
                    "avg": 133.905,
                    "min": 15.0,
                    "max": 280.0
                },
                "fragmentation": {
                    "avg": 0.044858,
                    "min": 0.0,
                    "max": 6.0
                },
                "injected_packet_rate": {
                    "avg": 0.00121042,
                    "min": 0.0004,
                    "max": 0.00253333
                },
                "accepted_packet_rate": {
                    "avg": 0.00121328,
                    "min": 0.0004,
                    "max": 0.00226667
                },
                "injected_flit_rate": {
                    "avg": 0.00484167,
                    "min": 0.0016,
                    "max": 0.0101333
                },
                "accepted_flit_rate": {
                    "avg": 0.00485299,
                    "min": 0.0016,
                    "max": 0.00906667
                },
                "injected_packet_size": {
                    "avg": 4.0
                },
                "accepted_packet_size": {
                    "avg": 3.99989
                },
                "hops": {
                    "avg": 7.1406
                },
                "total_ooo_packets": 0,
                "peak_rob_size": 0,
                "peak_robs_per_node": 0,
                "selection_function_storage_overhead": 0,
                "total_run_time": 38.1709,
                "number_of_deadlocked_runs": 0
            },
            "0.006": {
                "return_code": 0,
                "status": "Success",
                "runtime": 28.556944370269775,
                "cdg_check": "unknown",
                "packet_latency": {
                    "avg": 165.529,
                    "min": 18.0,
                    "max": 339.0
                },
                "network_latency": {
                    "avg": 128.094,
                    "min": 18.0,
                    "max": 246.0
                },
                "flit_latency": {
                    "avg": 125.369,
                    "min": 15.0,
                    "max": 243.0
                },
                "fragmentation": {
                    "avg": 0.0485537,
                    "min": 0.0,
                    "max": 7.0
                },
                "injected_packet_rate": {
                    "avg": 0.0015125,
                    "min": 0.0006,
                    "max": 0.0032
                },
                "accepted_packet_rate": {
                    "avg": 0.00150645,
                    "min": 0.0006,
                    "max": 0.0028
                },
                "injected_flit_rate": {
                    "avg": 0.00605,
                    "min": 0.0024,
                    "max": 0.0128
                },
                "accepted_flit_rate": {
                    "avg": 0.00602578,
                    "min": 0.0024,
                    "max": 0.0112
                },
                "injected_packet_size": {
                    "avg": 4.0
                },
                "accepted_packet_size": {
                    "avg": 4.0
                },
                "hops": {
                    "avg": 6.6844
                },
                "total_ooo_packets": 0,
                "peak_rob_size": 0,
                "peak_robs_per_node": 0,
                "selection_function_storage_overhead": 0,
                "total_run_time": 28.4154,
                "number_of_deadlocked_runs": 0
            },
            "0.007": {
                "return_code": 0,
                "status": "Success",
                "runtime": 47.06796430051327,
                "cdg_check": "unknown",
                "packet_latency": {
                    "avg": 163.28,
                    "min": 18.0,
                    "max": 386.0
                },
                "network_latency": {
                    "avg": 125.686,
                    "min": 18.0,
                    "max": 291.0
                },
                "flit_latency": {
                    "avg": 122.702,
                    "min": 15.0,
                    "max": 288.0
                },
                "fragmentation": {
                    "avg": 0.0444352,
                    "min": 0.0,
                    "max": 6.0
                },
                "injected_packet_rate": {
                    "avg": 0.00188073,
                    "min": 0.000933333,
                    "max": 0.00333333
                },
                "accepted_packet_rate": {
                    "avg": 0.00188047,
                    "min": 0.000933333,
                    "max": 0.00426667
                },
                "injected_flit_rate": {
                    "avg": 0.00752292,
                    "min": 0.00373333,
                    "max": 0.0133333
                },
                "accepted_flit_rate": {
                    "avg": 0.00752187,
                    "min": 0.00373333,
                    "max": 0.0170667
                },
                "injected_packet_size": {
                    "avg": 4.0
                },
                "accepted_packet_size": {
                    "avg": 4.0
                },
                "hops": {
                    "avg": 6.53537
                },
                "total_ooo_packets": 0,
                "peak_rob_size": 0,
                "peak_robs_per_node": 0,
                "selection_function_storage_overhead": 0,
                "total_run_time": 46.931,
                "number_of_deadlocked_runs": 0
            },
            "0.008": {
                "return_code": 0,
                "status": "Success",
                "runtime": 27.834904327988625,
                "cdg_check": "unknown",
                "packet_latency": {
                    "avg": 165.523,
                    "min": 18.0,
                    "max": 365.0
                },
                "network_latency": {
                    "avg": 127.782,
                    "min": 18.0,
                    "max": 293.0
                },
                "flit_latency": {
                    "avg": 124.797,
                    "min": 15.0,
                    "max": 290.0
                },
                "fragmentation": {
                    "avg": 0.0408004,
                    "min": 0.0,
                    "max": 9.0
                },
                "injected_packet_rate": {
                    "avg": 0.00200469,
                    "min": 0.0008,
                    "max": 0.00373333
                },
                "accepted_packet_rate": {
                    "avg": 0.00200885,
                    "min": 0.000533333,
                    "max": 0.0032
                },
                "injected_flit_rate": {
                    "avg": 0.00801927,
                    "min": 0.0032,
                    "max": 0.0149333
                },
                "accepted_flit_rate": {
                    "avg": 0.00803516,
                    "min": 0.00213333,
                    "max": 0.0128
                },
                "injected_packet_size": {
                    "avg": 4.00026
                },
                "accepted_packet_size": {
                    "avg": 3.99987
                },
                "hops": {
                    "avg": 6.704
                },
                "total_ooo_packets": 0,
                "peak_rob_size": 0,
                "peak_robs_per_node": 0,
                "selection_function_storage_overhead": 0,
                "total_run_time": 27.698,
                "number_of_deadlocked_runs": 0
            },
            "0.009": {
                "return_code": 0,
                "status": "Success",
                "runtime": 37.37950053811073,
                "cdg_check": "unknown",
                "packet_latency": {
                    "avg": 162.567,
                    "min": 18.0,
                    "max": 350.0
                },
                "network_latency": {
                    "avg": 124.79,
                    "min": 18.0,
                    "max": 259.0
                },
                "flit_latency": {
                    "avg": 121.751,
                    "min": 15.0,
                    "max": 256.0
                },
                "fragmentation": {
                    "avg": 0.0505034,
                    "min": 0.0,
                    "max": 7.0
                },
                "injected_packet_rate": {
                    "avg": 0.00232793,
                    "min": 0.0012,
                    "max": 0.0038
                },
                "accepted_packet_rate": {
                    "avg": 0.00232812,
                    "min": 0.0012,
                    "max": 0.0044
                },
                "injected_flit_rate": {
                    "avg": 0.00931172,
                    "min": 0.0048,
                    "max": 0.0152
                },
                "accepted_flit_rate": {
                    "avg": 0.0093125,
                    "min": 0.0048,
                    "max": 0.0176
                },
                "injected_packet_size": {
                    "avg": 4.0
                },
                "accepted_packet_size": {
                    "avg": 4.0
                },
                "hops": {
                    "avg": 6.54622
                },
                "total_ooo_packets": 0,
                "peak_rob_size": 0,
                "peak_robs_per_node": 0,
                "selection_function_storage_overhead": 0,
                "total_run_time": 37.241,
                "number_of_deadlocked_runs": 0
            },
            "0.01": {
                "return_code": 0,
                "status": "Success",
                "runtime": 31.640628457069397,
                "cdg_check": "unknown",
                "packet_latency": {
                    "avg": 166.611,
                    "min": 18.0,
                    "max": 393.0
                },
                "network_latency": {
                    "avg": 128.423,
                    "min": 18.0,
                    "max": 350.0
                },
                "flit_latency": {
                    "avg": 125.393,
                    "min": 15.0,
                    "max": 347.0
                },
                "fragmentation": {
                    "avg": 0.0911252,
                    "min": 0.0,
                    "max": 8.0
                },
                "injected_packet_rate": {
                    "avg": 0.00263099,
                    "min": 0.0008,
                    "max": 0.00453333
                },
                "accepted_packet_rate": {
                    "avg": 0.00262057,
                    "min": 0.000533333,
                    "max": 0.0048
                },
                "injected_flit_rate": {
                    "avg": 0.010524,
                    "min": 0.0032,
                    "max": 0.0181333
                },
                "accepted_flit_rate": {
                    "avg": 0.0104823,
                    "min": 0.00213333,
                    "max": 0.0192
                },
                "injected_packet_size": {
                    "avg": 4.0
                },
                "accepted_packet_size": {
                    "avg": 4.0
                },
                "hops": {
                    "avg": 6.89808
                },
                "total_ooo_packets": 0,
                "peak_rob_size": 0,
                "peak_robs_per_node": 0,
                "selection_function_storage_overhead": 0,
                "total_run_time": 31.5038,
                "number_of_deadlocked_runs": 0
            },
            "0.011": {
                "return_code": 2,
                "status": "Unstable simulation",
                "runtime": 81.7751332372427,
                "cdg_check": "unknown",
                "packet_latency": {
                    "avg": 169.897,
                    "min": 18.0,
                    "max": 355.0
                },
                "network_latency": {
                    "avg": 131.756,
                    "min": 18.0,
                    "max": 276.0
                },
                "flit_latency": {
                    "avg": 128.79,
                    "min": 15.0,
                    "max": 273.0
                },
                "fragmentation": {
                    "avg": 0.0697841,
                    "min": 0.0,
                    "max": 9.0
                },
                "injected_packet_rate": {
                    "avg": 0.00243984,
                    "min": 0.00108571,
                    "max": 0.00392857
                },
                "accepted_packet_rate": {
                    "avg": 0.00218036,
                    "min": 0.00114286,
                    "max": 0.00354286
                },
                "injected_flit_rate": {
                    "avg": 0.00975971,
                    "min": 0.00434286,
                    "max": 0.0157143
                },
                "accepted_flit_rate": {
                    "avg": NaN,
                    "min": 0.00457143,
                    "max": 0.0141714
                },
                "total_run_time": 81.6165,
                "number_of_deadlocked_runs": 0
            },
            "0.1": {
                "return_code": 2,
                "status": "Unstable simulation",
                "runtime": 13.363894522190094,
                "cdg_check": "unknown",
                "packet_latency": {
                    "avg": 169.339,
                    "min": 18.0,
                    "max": 400.0
                },
                "network_latency": {
                    "avg": 123.238,
                    "min": 18.0,
                    "max": 317.0
                },
                "flit_latency": {
                    "avg": 119.949,
                    "min": 15.0,
                    "max": 314.0
                },
                "fragmentation": {
                    "avg": 0.378539,
                    "min": 0.0,
                    "max": 10.0
                },
                "injected_packet_rate": {
                    "avg": 0.00320703,
                    "min": 0.00045,
                    "max": 0.0084
                },
                "accepted_packet_rate": {
                    "avg": 0.00157266,
                    "min": 0.0,
                    "max": 0.00625
                },
                "injected_flit_rate": {
                    "avg": 0.0128281,
                    "min": 0.0018,
                    "max": 0.0336
                },
                "accepted_flit_rate": {
                    "avg": NaN,
                    "min": 0.0,
                    "max": 0.025
                },
                "total_run_time": 13.2224,
                "number_of_deadlocked_runs": 0
            }
        },
        "booksim_config": {
            "deadlock_attempts": 10,
            "seed": "time",
            "ignore_cycles": 1,
            "trace_time_out": 7200,
            "precision": 0.001,
            "saturation_factor": 2,
            "router_latency": 3,
            "warmup_periods": 1,
            "sim_count": 1,
            "hold_switch_for_packet": 0,
            "vc_allocator": "separable_input_first",
            "sw_allocator": "separable_input_first",
            "alloc_iters": 1,
            "wait_for_tail_credit": 0,
            "priority": "none",
            "injection_rate_uses_flits": 1,
            "deadlock_warn_timeout": 200000,
            "time_limit": 43200,
            "latency_thres": 5000.0,
            "routing_function": "multi_routing",
            "modular_routing_function": "left_right",
            "modular_selection_function": "adaptive",
            "num_vcs": 4,
            "vc_buf_size": 16,
            "packet_size": 4,
            "message_size": 16,
            "in_order_ratio": 0.5,
            "n_entropy_bits": 8,
            "threshold_mode": "bounded",
            "mode": "traffic",
            "traffic": "uniform",
            "trace_file": null,
            "sample_period": 20000,
            "repetition": 2
        }
    }
]